textcrypt.py
textcrypt/main.py
textcrypt-0.0.8.dist-info/DESCRIPTION.rst
textcrypt-0.0.8.dist-info/METADATA
textcrypt-0.0.8.dist-info/RECORD
textcrypt-0.0.8.dist-info/WHEEL
textcrypt-0.0.8.dist-info/metadata.json
textcrypt-0.0.8.dist-info/top_level.txt
